[
  {
    "id": "prop_001",
    "userId": "user_001",
    "title": "Luxury 3BHK Apartment in Bandra",
    "description": "Spacious 3BHK apartment with modern amenities and great city views",
    "type": "sale",
    "category": "residential",
    "propertyType": "apartment",
    "price": 15000000,
    "currency": "INR",
    "pricePerSqft": 12500,
    "negotiable": true,
    "area": 1200,
    "builtUpArea": 1200,
    "carpetArea": 1000,
    "bedrooms": 3,
    "bathrooms": 2,
    "balconies": 2,
    "parking": 1,
    "floor": 8,
    "totalFloors": 15,
    "address": "Bandra West, Mumbai",
    "city": "Mumbai",
    "state": "Maharashtra",
    "country": "India",
    "pincode": "400050",
    "locality": "Bandra West",
    "landmark": "Near Bandra Station",
    "latitude": 19.0596,
    "longitude": 72.8295,
    "furnishing": "semi-furnished",
    "status": "active",
    "availability": "immediate",
    "possessionDate": "2024-12-15T00:00:00Z",
    "featured": true,
    "premium": true,
    "verified": true,
    "views": 1250,
    "inquiries": 45,
    "favorites": 23,
    "shares": 12,
    "ageOfProperty": 2,
    "facing": "north",
    "source": "direct",
    "contactPreference": "both",
    "bestTimeToCall": "evening",
    "createdAt": "2024-01-20T10:00:00Z",
    "updatedAt": "2024-12-01T14:30:00Z",
    "publishedAt": "2024-01-20T10:00:00Z",
    "expiresAt": "2025-01-20T10:00:00Z",
    "images": [
      "https://example.com/images/prop1_1.jpg",
      "https://example.com/images/prop1_2.jpg",
      "https://example.com/images/prop1_3.jpg"
    ],
    "amenities": [
      "Swimming Pool",
      "Gym",
      "Security",
      "Parking",
      "Elevator"
    ],
    "features": [
      "Modular Kitchen",
      "Wooden Flooring",
      "Balcony",
      "Natural Light"
    ],
    "tags": [
      "luxury",
      "bandra",
      "3bhk",
      "apartment"
    ]
  }
]